keyword_spacy/__init__.py
keyword_spacy/components.py
keyword_spacy-0.1.1.dist-info/METADATA
keyword_spacy-0.1.1.dist-info/WHEEL
keyword_spacy-0.1.1.dist-info/top_level.txt
keyword_spacy-0.1.1.dist-info/RECORD
