Metadata-Version: 2.1
Name: keyword-spacy
Version: 0.1.1
Summary: A spaCy pipeline component for extracting keywords from text using cosine similarity.
Home-page: https://github.com/wjbmattingly/keyword-spacy
Author: WJB Mattingly
Classifier: Intended Audience :: Developers
Classifier: Intended Audience :: Science/Research
Classifier: License :: OSI Approved :: MIT License
Classifier: Programming Language :: Python :: 3
Classifier: Programming Language :: Python :: 3.6
Classifier: Programming Language :: Python :: 3.7
Classifier: Programming Language :: Python :: 3.8
Classifier: Topic :: Scientific/Engineering :: Artificial Intelligence
Requires-Dist: spacy (>=3.0)
